{
  "parent":"endreborn:endreborn/root",
  "display":{
    "icon":{
      "count": 1,
      "id": "endreborn:endorium_block"
    },
    "title":{
      "translate":"advancements.endreborn.endorium_block.title"
    },
    "description":{
      "translate":"advancements.endreborn.endorium_block.description"
    },
    "frame":"goal",
    "show_toast":false,
    "announce_to_chat":true,
    "hidden":false
  },
  "criteria":{
    "endorium_block":{
      "conditions":{
        "items":[
          {
            "items":[
              "endreborn:endorium_block"
            ]
          }
        ]
      },
      "trigger":"minecraft:inventory_changed"
    }
  },
  "requirements":[
    [
      "endorium_block"
    ]
  ]
}