{
  "display": {
    "icon":{
      "count": 1,
      "id": "endreborn:tungsten_hammer"
    },
    "title": {
      "translate": "advancements.endreborn.root.title"
    },
    "description": {
      "translate": "advancements.endreborn.root.description"
    },
    "show_toast": true,
    "announce_to_chat": false,
    "hidden": false,
    "background": "endreborn:textures/block/farstone.png"
  },
  "criteria": {
    "endorium_nugget": {
      "conditions": {
        "items": [
          {
            "items": [
              "endreborn:endorium_nugget"
            ]
          }
        ]
      },
      "trigger": "minecraft:inventory_changed"
    }
  },
  "requirements": [
    [
      "endorium_nugget"
    ]
  ]
}